pretix_dbvat/__init__.py
pretix_dbvat/apps.py
pretix_dbvat/forms.py
pretix_dbvat/helpers.py
pretix_dbvat/models.py
pretix_dbvat/signals.py
pretix_dbvat/urls.py
pretix_dbvat/views.py
pretix_dbvat/locale/django.pot
pretix_dbvat/locale/de/LC_MESSAGES/django.mo
pretix_dbvat/locale/de/LC_MESSAGES/django.po
pretix_dbvat/locale/de_Informal/.gitkeep
pretix_dbvat/locale/de_Informal/LC_MESSAGES/django.mo
pretix_dbvat/locale/de_Informal/LC_MESSAGES/django.po
pretix_dbvat/migrations/0001_initial.py
pretix_dbvat/migrations/0002_rename_itemproduct_itemdbvatconfig.py
pretix_dbvat/migrations/__init__.py
pretix_dbvat/static/pretix_dbvat/.gitkeep
pretix_dbvat/static/pretix_dbvat/db-logo.svg
pretix_dbvat/static/pretix_dbvat/pretix-dbvat.scss
pretix_dbvat/templates/pretix_dbvat/.gitkeep
pretix_dbvat/templates/pretix_dbvat/bulk.html
pretix_dbvat/templates/pretix_dbvat/delete.html
pretix_dbvat/templates/pretix_dbvat/detail.html
pretix_dbvat/templates/pretix_dbvat/index.html
pretix_dbvat/templates/pretix_dbvat/order_position_info.html
pretix_dbvat/templates/pretix_dbvat/presale_head.html
pretix_dbvat-1.1.0.dist-info/LICENSE
pretix_dbvat-1.1.0.dist-info/METADATA
pretix_dbvat-1.1.0.dist-info/WHEEL
pretix_dbvat-1.1.0.dist-info/entry_points.txt
pretix_dbvat-1.1.0.dist-info/top_level.txt
pretix_dbvat-1.1.0.dist-info/RECORD
