Metadata-Version: 2.1
Name: pretix-dbvat
Version: 1.1.0
Summary: Distribute Deutsche Bahn Veranstaltungsrabatt (DB VAT) eCoupons to your attendees
Author-email: pretix team <support@pretix.eu>
Maintainer-email: pretix team <support@pretix.eu>
License: Apache
Project-URL: homepage, https://github.com/pretix/pretix-dbvat/
Project-URL: repository, https://github.com/pretix/pretix-dbvat/
Keywords: pretix
License-File: LICENSE
